signal_unkillable
