Metadata-Version: 1.0
Name: signal-unkillable
Version: 0.0.9
Summary: A python interface to the SIGNAL_UNKILLABLE flag in linux.
Home-page: UNKNOWN
Author: UNKNOWN
Author-email: UNKNOWN
License: UNKNOWN
Platform: UNKNOWN
